[
    {
      "userId": 1,
      "id": 1,
      "title": "Crear un webApp usando react",
      "body": "Se usó la estructura de funciones ya que permiten el uso de hooks, los cuales no funcionan dentro de clases"
    },
    {
      "userId": 1,
      "id": 2,
      "title": "Project Architecture",
      "body": "Determinar los pasos que se deben tomar para el desarrollo de este proyecto, asi como los recursos necesarios"
    },
    {
      "userId": 1,
      "id": 3,
      "title": "Manejo de datos",
      "body": "Desarrollar un backend confiable, seguro y rápido"
    },
    {
      "userId": 1,
      "id": 4,
      "title": "User Interface",
      "body": "Desarrollar un front en agradable y funcional"
    }
 ]
